lzstring/__init__.py
lzstring-1.0.3.dist-info/DESCRIPTION.rst
lzstring-1.0.3.dist-info/METADATA
lzstring-1.0.3.dist-info/metadata.json
lzstring-1.0.3.dist-info/RECORD
lzstring-1.0.3.dist-info/top_level.txt
lzstring-1.0.3.dist-info/WHEEL
