Metadata-Version: 1.1
Name: lzstring
Version: 1.0.3
Summary: lz-string for python
Home-page: https://github.com/gkovacs/lz-string-python
Author: Geza Kovacs
Author-email: geza0kovacs@gmail.com
License: UNKNOWN
Download-URL: https://github.com/gkovacs/lz-string-python
Platform: UNKNOWN
Classifier: Development Status :: 3 - Alpha
Classifier: Intended Audience :: Developers
Classifier: Natural Language :: English
Classifier: License :: OSI Approved :: MIT License
Classifier: Programming Language :: Python
Classifier: Programming Language :: Python :: 2
Classifier: Programming Language :: Python :: 2.6
Classifier: Programming Language :: Python :: 2.7
Classifier: Programming Language :: Python :: 3
Classifier: Programming Language :: Python :: 3.1
Classifier: Programming Language :: Python :: 3.2
Classifier: Programming Language :: Python :: 3.3
